order_management_pkg/__init__.py
order_management_your_username_here-0.1.0.dist-info/METADATA
order_management_your_username_here-0.1.0.dist-info/WHEEL
order_management_your_username_here-0.1.0.dist-info/licenses/LICENSE
order_management_your_username_here-0.1.0.dist-info/RECORD
