Metadata-Version: 2.3
Name: order-management-YOUR_USERNAME_HERE
Version: 0.1.0
Summary: AWS Order Management System with DynamoDB, S3, and SNS integration
Author-email: Your Name <your.email@example.com>
Classifier: License :: OSI Approved :: MIT License
Classifier: Operating System :: OS Independent
Classifier: Programming Language :: Python :: 3
Requires-Python: >=3.8
Requires-Dist: boto3>=1.26.0
